pyfp/__init__.py
pyfp/helpers.py
pyfp/match.py
pyfp/option.py
pyfp/pipe.py
pyfp-0.1.5.dist-info/WHEEL
pyfp-0.1.5.dist-info/METADATA
pyfp-0.1.5.dist-info/RECORD
