Metadata-Version: 2.1
Name: pyfp
Version: 0.1.5
Summary: A library for functional programming patterns.
Author: Brett Kolodny
Author-email: brettkolodny@gmail.com
Requires-Python: >=3.8,<4.0
Classifier: Programming Language :: Python :: 3
Classifier: Programming Language :: Python :: 3.8
Classifier: Programming Language :: Python :: 3.9
